contracts/__init__.py
contracts/contracts.py
contracts/exceptions.py
contracts/qualifiers.py
tests/__init__.py
tests/test_contracts.py
tests/test_qualifiers.py
python_contracts-0.1.4.dist-info/LICENSE
python_contracts-0.1.4.dist-info/METADATA
python_contracts-0.1.4.dist-info/WHEEL
python_contracts-0.1.4.dist-info/top_level.txt
python_contracts-0.1.4.dist-info/RECORD
