Metadata-Version: 2.1
Name: python-contracts
Version: 0.1.4
Summary: Function contracts for Python
Home-page: https://github.com/gvjacob/contracts
Author: Gino Jacob
Author-email: gvjacob@outlook.com
License: UNKNOWN
Platform: UNKNOWN
Classifier: Programming Language :: Python :: 3
Classifier: License :: OSI Approved :: MIT License
Classifier: Operating System :: OS Independent
